pingan_gpt_client/__init__.py
pingan_gpt_client/pingan_gpt.py
pingan_gpt_client-0.3.3.dist-info/METADATA
pingan_gpt_client-0.3.3.dist-info/WHEEL
pingan_gpt_client-0.3.3.dist-info/RECORD
