Metadata-Version: 2.1
Name: pingan-gpt-client
Version: 0.3.3
Summary: sdk for pingan tech gpt
Author: yanyongwen712
Author-email: yanyongwen712@pingan.com.cn
Requires-Python: >=3.7,<4.0
Classifier: Programming Language :: Python :: 3
Classifier: Programming Language :: Python :: 3.7
Classifier: Programming Language :: Python :: 3.8
Classifier: Programming Language :: Python :: 3.9
Classifier: Programming Language :: Python :: 3.10
Classifier: Programming Language :: Python :: 3.11
Classifier: Programming Language :: Python :: 3.12
Requires-Dist: grequests (>=0.7.0,<0.8.0)
Requires-Dist: pycryptodome (>=3.20.0,<4.0.0)
